boldi/_sitebuilder_version.py
boldi/sitebuilder.py
boldi_sitebuilder-0.9.7.dist-info/METADATA
boldi_sitebuilder-0.9.7.dist-info/WHEEL
boldi_sitebuilder-0.9.7.dist-info/entry_points.txt
boldi_sitebuilder-0.9.7.dist-info/RECORD
