Metadata-Version: 2.4
Name: boldi-sitebuilder
Version: 0.9.7
Summary: boldi.sitebuilder part of Boldi's Python libraries
Author-email: Boldizsár Palotás <boldizsar.palotas@gmail.com>
License: MIT
Requires-Python: >=3.10
Requires-Dist: boldi-cli==0.9.7
Requires-Dist: jinja2
Requires-Dist: markdown-it-py[linkify,plugins]
